docs/source/conf.py
lightning_sdk/__init__.py
lightning_sdk/__version__.py
lightning_sdk/agents.py
lightning_sdk/ai_hub.py
lightning_sdk/base_studio.py
lightning_sdk/constants.py
lightning_sdk/exceptions.py
lightning_sdk/helpers.py
lightning_sdk/k8s_cluster.py
lightning_sdk/lit_container.py
lightning_sdk/machine.py
lightning_sdk/models.py
lightning_sdk/organization.py
lightning_sdk/owner.py
lightning_sdk/plugin.py
lightning_sdk/sandbox.py
lightning_sdk/serve.py
lightning_sdk/status.py
lightning_sdk/studio.py
lightning_sdk/teamspace.py
lightning_sdk/user.py
lightning_sdk/api/__init__.py
lightning_sdk/api/agents_api.py
lightning_sdk/api/ai_hub_api.py
lightning_sdk/api/base_studio_api.py
lightning_sdk/api/cloud_account_api.py
lightning_sdk/api/deployment_api.py
lightning_sdk/api/job_api.py
lightning_sdk/api/k8s_api.py
lightning_sdk/api/license_api.py
lightning_sdk/api/lit_container_api.py
lightning_sdk/api/llm_api.py
lightning_sdk/api/mmt_api.py
lightning_sdk/api/org_api.py
lightning_sdk/api/pipeline_api.py
lightning_sdk/api/studio_api.py
lightning_sdk/api/teamspace_api.py
lightning_sdk/api/user_api.py
lightning_sdk/api/utils.py
lightning_sdk/cli/__init__.py
lightning_sdk/cli/entrypoint.py
lightning_sdk/cli/groups.py
lightning_sdk/cli/base_studio/__init__.py
lightning_sdk/cli/base_studio/list.py
lightning_sdk/cli/config/__init__.py
lightning_sdk/cli/config/get.py
lightning_sdk/cli/config/set.py
lightning_sdk/cli/config/show.py
lightning_sdk/cli/job/__init__.py
lightning_sdk/cli/legacy/__init__.py
lightning_sdk/cli/legacy/ai_hub.py
lightning_sdk/cli/legacy/clusters_menu.py
lightning_sdk/cli/legacy/configure.py
lightning_sdk/cli/legacy/connect.py
lightning_sdk/cli/legacy/create.py
lightning_sdk/cli/legacy/delete.py
lightning_sdk/cli/legacy/docker_cli.py
lightning_sdk/cli/legacy/download.py
lightning_sdk/cli/legacy/entrypoint.py
lightning_sdk/cli/legacy/exceptions.py
lightning_sdk/cli/legacy/generate.py
lightning_sdk/cli/legacy/inspection.py
lightning_sdk-2025.12.17.dist-info/LICENSE
lightning_sdk-2025.12.17.dist-info/METADATA
lightning_sdk-2025.12.17.dist-info/WHEEL
lightning_sdk-2025.12.17.dist-info/entry_points.txt
lightning_sdk-2025.12.17.dist-info/top_level.txt
lightning_sdk-2025.12.17.dist-info/RECORD
