Metadata-Version: 2.1
Name: lightning_sdk
Version: 2025.12.17
Summary: SDK to develop using Lightning AI Studios
Author-email: Lightning-AI <justus@lightning.ai>
License: MIT License
Project-URL: Homepage, https://lightning.ai
Project-URL: Documentation, https://lightning.ai/docs/overview/sdk-reference
Keywords: deep learning,machine learning,pytorch,AI
Classifier: Programming Language :: Python :: 3
Classifier: License :: OSI Approved :: MIT License
Requires-Python: >=3.8
License-File: LICENSE
Requires-Dist: backoff
Requires-Dist: click
Requires-Dist: docker
Requires-Dist: fastapi
Requires-Dist: packaging
Requires-Dist: pandas
Requires-Dist: pyjwt
Requires-Dist: pyyaml
Requires-Dist: requests
Requires-Dist: rich
Requires-Dist: simple-term-menu
Requires-Dist: six
Requires-Dist: tqdm
Requires-Dist: urllib3<=2.5.0
Requires-Dist: uvicorn
Requires-Dist: websocket-client
Requires-Dist: wget
Provides-Extra: serve
Requires-Dist: litserve>=0.2.5; extra == "serve"
